CHANGES.rst
CONTRIBUTORS.rst
MANIFEST.in
README.rst
setup.cfg
setup.py
docs/screenshot.png
wm/__init__.py
wm.sampledata.egg-info/PKG-INFO
wm.sampledata.egg-info/SOURCES.txt
wm.sampledata.egg-info/dependency_links.txt
wm.sampledata.egg-info/entry_points.txt
wm.sampledata.egg-info/namespace_packages.txt
wm.sampledata.egg-info/not-zip-safe
wm.sampledata.egg-info/requires.txt
wm.sampledata.egg-info/top_level.txt
wm/sampledata/__init__.py
wm/sampledata/browser.py
wm/sampledata/configure.zcml
wm/sampledata/images.py
wm/sampledata/interfaces.py
wm/sampledata/sampledata.pt
wm/sampledata/tests.py
wm/sampledata/utils.py
wm/sampledata/example/__init__.py
wm/sampledata/example/configure.zcml
wm/sampledata/example/portlet.html