Metadata-Version: 1.1
Name: wm.sampledata
Version: 0.5.2
Summary: UI and utility methods to generate sampledata for Plone projects
Home-page: https://github.com/collective/wm.sampledata
Author: Harald Friessnegger
Author-email: harald (at) webmeisterei dot com
License: GPL
Keywords: plone sampledata generation
Platform: UNKNOWN
Classifier: Programming Language :: Python
Classifier: Framework :: Plone
Classifier: Framework :: Plone :: 4.1
Classifier: Framework :: Plone :: 4.2
Classifier: Framework :: Plone :: 4.3
